azure/mgmt/paloaltonetworksngfw/__init__.py
azure/mgmt/paloaltonetworksngfw/_configuration.py
azure/mgmt/paloaltonetworksngfw/_palo_alto_networks_ngfw_mgmt_client.py
azure/mgmt/paloaltonetworksngfw/_patch.py
azure/mgmt/paloaltonetworksngfw/_version.py
azure/mgmt/paloaltonetworksngfw/py.typed
azure/mgmt/paloaltonetworksngfw/_utils/__init__.py
azure/mgmt/paloaltonetworksngfw/_utils/serialization.py
azure/mgmt/paloaltonetworksngfw/aio/__init__.py
azure/mgmt/paloaltonetworksngfw/aio/_configuration.py
azure/mgmt/paloaltonetworksngfw/aio/_palo_alto_networks_ngfw_mgmt_client.py
azure/mgmt/paloaltonetworksngfw/aio/_patch.py
azure/mgmt/paloaltonetworksngfw/aio/operations/__init__.py
azure/mgmt/paloaltonetworksngfw/aio/operations/_certificate_object_global_rulestack_operations.py
azure/mgmt/paloaltonetworksngfw/aio/operations/_certificate_object_local_rulestack_operations.py
azure/mgmt/paloaltonetworksngfw/aio/operations/_firewall_status_operations.py
azure/mgmt/paloaltonetworksngfw/aio/operations/_firewalls_operations.py
azure/mgmt/paloaltonetworksngfw/aio/operations/_fqdn_list_global_rulestack_operations.py
azure/mgmt/paloaltonetworksngfw/aio/operations/_fqdn_list_local_rulestack_operations.py
azure/mgmt/paloaltonetworksngfw/aio/operations/_global_rulestack_operations.py
azure/mgmt/paloaltonetworksngfw/aio/operations/_local_rules_operations.py
azure/mgmt/paloaltonetworksngfw/aio/operations/_local_rulestacks_operations.py
azure/mgmt/paloaltonetworksngfw/aio/operations/_metrics_object_firewall_operations.py
azure/mgmt/paloaltonetworksngfw/aio/operations/_operations.py
azure/mgmt/paloaltonetworksngfw/aio/operations/_palo_alto_networks_cloudngfw_operations_operations.py
azure/mgmt/paloaltonetworksngfw/aio/operations/_patch.py
azure/mgmt/paloaltonetworksngfw/aio/operations/_post_rules_operations.py
azure/mgmt/paloaltonetworksngfw/aio/operations/_pre_rules_operations.py
azure/mgmt/paloaltonetworksngfw/aio/operations/_prefix_list_global_rulestack_operations.py
azure_mgmt_paloaltonetworksngfw-1.1.0.dist-info/licenses/LICENSE
azure_mgmt_paloaltonetworksngfw-1.1.0.dist-info/METADATA
azure_mgmt_paloaltonetworksngfw-1.1.0.dist-info/WHEEL
azure_mgmt_paloaltonetworksngfw-1.1.0.dist-info/top_level.txt
azure_mgmt_paloaltonetworksngfw-1.1.0.dist-info/RECORD
